FastAnalytics/EDALL.py
FastAnalytics/Univariate_Analysis.py
FastAnalytics/__init__.py
FastAnalytics-0.0.4.dist-info/LICENSE
FastAnalytics-0.0.4.dist-info/METADATA
FastAnalytics-0.0.4.dist-info/WHEEL
FastAnalytics-0.0.4.dist-info/top_level.txt
FastAnalytics-0.0.4.dist-info/RECORD
